{
    "parameters": {
        "train_from_checkpoint": false,
        "num_tsteps": 35,
        "batch_size": 128,
        "DS_name": "FMNIST",
        "DS_classes": [
            0,
            1,
            4,
            5
        ],
        "DS_N_samples_train": 21760,
        "DS_N_samples_val": 2048,
        "DS_N_samples_test": 3900,
        "use_ratecoded_MNIST": true,
        "SNN_model": "tiled",
        "SNN_layer_widths": [
            [
                32,
                16
            ],
            [
                16,
                4
            ]
        ],
        "input_size": 32,
        "SNN_tile_counts": [
            2,
            1
        ],
        "SNN_lif_thresholds": [
            0.5,
            0.25
        ],
        "SNN_lif_betas": [
            0.99,
            0.99
        ],
        "SNN_lif_reset_mechanism": "zero",
        "ref_period_enabled": false,
        "ref_period_timesteps": 1,
        "comb_channel_spacing_hz": 50000000000.0,
        "comb_peak_channel_power_dbm": -12.0,
        "eoconv_unity_opt_P_per_WDM_channel_dbm": -12.0,
        "eoconv_spatial_dim_broadcast_divide_power": false,
        "sephia_post_divide_power": false,
        "sephia_specs": {
            "mrr_Q": 10000,
            "mrr_ER_db": 15.0,
            "mrr_IL_db": 0,
            "mrr_reso_shift_range_pm": -333.3333333333333
        },
        "use_bpds": true,
        "optimizer_lr": 0.04,
        "optimizer_scheduler_enabled": true,
        "optimizer_scheduler_type": "CosineAnnealingLR",
        "optimizer_scheduler_min_lr": 0,
        "optimizer_weight_decay": 0,
        "init_range_nonsigma": [
            -1,
            2
        ],
        "init_range_sigma": [
            0.9,
            1.1
        ],
        "dropout_enabled": true,
        "dropout_p": 0.15,
        "evaluate_untrained_model": true,
        "accuracy_from_membrane_potential": false,
        "configs_override": {
            "specs": {
                "mrr_Q": 10000,
                "mrr_ER_db": 15.0,
                "mrr_IL_db": 0.0,
                "mrr_reso_shift_range_pm": -396.8253968253968,
                "pds_noise_thermal_enabled": true,
                "pds_noise_shot_enabled": true
            }
        },
        "cuda_id": 6,
        "repeats": 5,
        "num_epochs": 20,
        "save_detailed_training_accuracies": true,
        "train_iteratively": false,
        "iterative_warmup_epochs": 0,
        "label": "RunD(NoDecay,LR=4e-2)_(FMN32=4)(100.0GHz,-12.0dBm)(10K,0.00dB,15dB)(RP=0)(Tiled=2)"
    },
    "confmat_test": [
        [
            801,
            53,
            45,
            56
        ],
        [
            43,
            882,
            19,
            17
        ],
        [
            41,
            26,
            861,
            39
        ],
        [
            14,
            4,
            20,
            919
        ]
    ],
    "train_loss": [
        1.3186739907545202,
        1.1989641757572398,
        1.0556050311116612,
        0.9395870348986457,
        0.8560076475143432,
        0.7991978820632486,
        0.7426458853132585,
        0.6998388395589941,
        0.6618421491454629,
        0.6203665729831247,
        0.5996078336940093,
        0.5786112397909164,
        0.5671520049081129,
        0.56225785928614,
        0.555167212731698,
        0.5502006656983319,
        0.5458191398312063,
        0.5400852874797933,
        0.5353991506730809,
        0.5380457048906999
    ],
    "val_loss": [
        1.3905848413705826,
        1.2599938288331032,
        1.1269192844629288,
        0.9965721257030964,
        0.8914671130478382,
        0.8423967771232128,
        0.7666664868593216,
        0.7244466878473759,
        0.6792024597525597,
        0.6186521239578724,
        0.606787484139204,
        0.5676206983625889,
        0.5515896454453468,
        0.5488316938281059,
        0.5593767780810595,
        0.5380278155207634,
        0.5400466695427895,
        0.5455026216804981,
        0.5230782981961966,
        0.5345216728746891,
        0.5186654720455408
    ],
    "val_accuracy": [
        22.802734375,
        67.3828125,
        85.791015625,
        85.205078125,
        88.57421875,
        88.232421875,
        87.744140625,
        88.330078125,
        88.916015625,
        88.916015625,
        88.330078125,
        89.6484375,
        90.380859375,
        89.306640625,
        90.0390625,
        89.6484375,
        89.990234375,
        88.8671875,
        90.33203125,
        89.16015625,
        89.94140625
    ],
    "val_accuracy_per_class": [
        [
            90.81999969482422,
            7.75000038146973,
            80.80999755859375,
            91.51000213623047
        ],
        [
            88.16000366210938,
            78.6500061035156,
            87.13999938964844,
            89.37999725341797
        ],
        [
            91.62999725341797,
            79.7699966430664,
            78.69000244140625,
            91.12000274658203
        ],
        [
            86.33000183105469,
            89.9800033569336,
            83.30000305175781,
            94.58999633789062
        ],
        [
            84.08000183105469,
            90.94000244140625,
            83.69000244140625,
            94.0199966430664
        ],
        [
            79.58999633789062,
            87.27999877929688,
            86.94999694824219,
            96.72000122070312
        ],
        [
            83.87999725341797,
            85.73999786376953,
            85.22000122070312,
            98.26000213623047
        ],
        [
            84.9000015258789,
            89.79000091552734,
            84.83999633789062,
            95.94999694824219
        ],
        [
            87.55000305175781,
            85.93000030517578,
            85.5999984741211,
            96.52999877929688
        ],
        [
            84.9000015258789,
            89.79000091552734,
            80.41999816894531,
            98.06999969482422
        ],
        [
            82.6500015258789,
            91.70999908447266,
            85.41000366210938,
            98.45999908447266
        ],
        [
            88.16000366210938,
            89.20999908447266,
            86.76000213623047,
            97.30000305175781
        ],
        [
            84.9000015258789,
            92.29000091552734,
            85.22000122070312,
            94.58999633789062
        ],
        [
            87.95999908447266,
            88.44000244140625,
            87.33000183105469,
            96.33000183105469
        ],
        [
            87.13999938964844,
            89.79000091552734,
            86.76000213623047,
            94.79000091552734
        ],
        [
            85.70999908447266,
            89.9800033569336,
            87.91000366210938,
            96.13999938964844
        ],
        [
            88.56999969482422,
            87.27999877929688,
            86.76000213623047,
            92.86000061035156
        ],
        [
            85.51000213623047,
            90.55999755859375,
            87.72000122070312,
            97.30000305175781
        ],
        [
            82.6500015258789,
            91.13999938964844,
            86.37000274658203,
            96.13999938964844
        ],
        [
            85.51000213623047,
            91.13999938964844,
            86.37000274658203,
            96.52999877929688
        ]
    ]
}